pysaucenao/__init__.py
pysaucenao/errors.py
pysaucenao/filters.py
pysaucenao/indexes.py
pysaucenao/models.py
pysaucenao/results.py
pysaucenao/saucenao.py
pysaucenao-2.0.1.dist-info/METADATA
pysaucenao-2.0.1.dist-info/WHEEL
pysaucenao-2.0.1.dist-info/licenses/LICENSE
pysaucenao-2.0.1.dist-info/RECORD
